{
  "title": "Imaizumi Brings All The Gyarus to His House",
  "description": "Some gyarus have decided to use Imaizumi's house as a gathering spot to play video games and eat snacks. When Reina gets bored with video games, she sets her sights on another toy in the house: Imaizumi himself...",
  "artist": "Norigorou",
  "author": "Norigorou",
  "cover": "https://files.catbox.moe/yzvmor.jpg",
  "chapters": {
    "001": {
      "title": "",
      "last_updated": "1775832681",
      "groups": {
        "Xiffy": "/proxy/api/imgchest/chapter/n87w89w9b7x"
      }
    },
    "002": {
      "title": "",
      "last_updated": "1775832718",
      "groups": {
        "Xiffy": "/proxy/api/imgchest/chapter/qe4gzmomb7j"
      }
    },
    "003": {
      "title": "",
      "last_updated": "1775832724",
      "groups": {
        "Xiffy": "/proxy/api/imgchest/chapter/qb4zl5a5v7j"
      }
    },
    "006": {
      "title": "",
      "last_updated": "1775832845",
      "groups": {
        "Xiffy": "/proxy/api/imgchest/chapter/5xy2xqwn84l"
      }
    },
    "007": {
      "title": "",
      "last_updated": "1775832885",
      "groups": {
        "Xiffy": "/proxy/api/imgchest/chapter/vj4j5erne78"
      }
    },
    "005": {
      "title": "",
      "last_updated": "1775832950",
      "groups": {
        "Xiffy": "/proxy/api/imgchest/chapter/md7oda659yp"
      }
    },
    "004": {
      "title": "",
      "last_updated": "1775833030",
      "groups": {
        "Xiffy": "/proxy/api/imgchest/chapter/6eyr3apa6yp"
      }
    },
    "008": {
      "title": "",
      "last_updated": "1775833037",
      "groups": {
        "Xiffy": "/proxy/api/imgchest/chapter/ne7brl83vy5"
      }
    },
    "009": {
      "title": "",
      "last_updated": "1775833688",
      "groups": {
        "Xiffy": "/proxy/api/imgchest/chapter/ljyqman6k72"
      }
    }
  }
}