{
  "title": "Sex Partners Delivered to Your Door",
  "description": "Sunao’s life is one dreary, lonely day after another, just as it has been for the past eight years since he started his job. There’s nothing to look forward to and he doesn’t even have the energy to try to improve his situation. That all changes when he answers the door to see two young women, assigned to live with him as part of a program designed to combat falling birth rates. With their help, maybe things can turn around.",
  "artist": "Freedom Prophet",
  "author": "Freedom Prophet",
  "cover": "https://files.catbox.moe/t3sk2p.jpg",
  "chapters": {
    "003": {
      "title": "",
      "last_updated": "1776152129",
      "groups": {
        "Xiffy": "/proxy/api/imgchest/chapter/vj4j55q8978"
      }
    },
    "004": {
      "title": "",
      "last_updated": "1776152129",
      "groups": {
        "Xiffy": "/proxy/api/imgchest/chapter/5xy2xxb234l"
      }
    },
    "002": {
      "title": "",
      "last_updated": "1776152131",
      "groups": {
        "Xiffy": "/proxy/api/imgchest/chapter/wl7lll3o37x"
      }
    },
    "001": {
      "title": "",
      "last_updated": "1776152134",
      "groups": {
        "Xiffy": "/proxy/api/imgchest/chapter/ljyqmm82x72"
      }
    }
  }
}