{
  "title": "Shigeo's Adventures",
  "description": "Shigeo and his adventures written by Freehand Tamashii",
  "artist": "Freehand Tamashii",
  "author": "Freehand Tamashii",
  "cover": "",
  "status": "Completed",
  "chapters": {
    "1": {
      "title": "01 - Aunt Toshie Stays Over",
      "volume": "1",
      "last_updated": "1761557008",
      "groups": {
        "Xiffy": [
          "https://files.catbox.moe/xsm2je.webp",
          "https://files.catbox.moe/pup322.webp",
          "https://files.catbox.moe/3z5399.webp",
          "https://files.catbox.moe/f4apbm.webp",
          "https://files.catbox.moe/0xmjn3.webp",
          "https://files.catbox.moe/did1jl.webp",
          "https://files.catbox.moe/cr5yb4.webp",
          "https://files.catbox.moe/1cip1z.webp",
          "https://files.catbox.moe/luknay.webp",
          "https://files.catbox.moe/235be9.webp",
          "https://files.catbox.moe/dy52fl.webp",
          "https://files.catbox.moe/zmyj59.webp",
          "https://files.catbox.moe/h61vca.webp",
          "https://files.catbox.moe/rbrwu6.webp",
          "https://files.catbox.moe/7r7m5v.webp",
          "https://files.catbox.moe/w9hzii.webp",
          "https://files.catbox.moe/fisizw.webp",
          "https://files.catbox.moe/1j2g01.webp",
          "https://files.catbox.moe/y5ju9m.webp",
          "https://files.catbox.moe/qr3f0f.webp",
          "https://files.catbox.moe/yqabct.webp",
          "https://files.catbox.moe/jf12fe.webp",
          "https://files.catbox.moe/r3ja4g.webp",
          "https://files.catbox.moe/yx3ah0.webp",
          "https://files.catbox.moe/ztv7ze.webp",
          "https://files.catbox.moe/sf7h6s.webp",
          "https://files.catbox.moe/us2rxz.webp",
          "https://files.catbox.moe/qyye93.webp",
          "https://files.catbox.moe/mtdokx.webp",
          "https://files.catbox.moe/xy4jjh.webp",
          "https://files.catbox.moe/oa7p8z.webp",
          "https://files.catbox.moe/qap01a.webp",
          "https://files.catbox.moe/as03n7.webp",
          "https://files.catbox.moe/7j34wt.webp",
          "https://files.catbox.moe/9aiuga.webp",
          "https://files.catbox.moe/9vio7b.webp",
          "https://files.catbox.moe/ef5bn2.webp",
          "https://files.catbox.moe/40cu64.webp",
          "https://files.catbox.moe/wvvf53.webp",
          "https://files.catbox.moe/basfka.webp",
          "https://files.catbox.moe/3i501a.webp",
          "https://files.catbox.moe/xng90a.webp",
          "https://files.catbox.moe/tv90si.webp",
          "https://files.catbox.moe/xucgn7.webp",
          "https://files.catbox.moe/cn0nxj.webp"
        ]
      }
    },
    "2": {
      "title": "02 - NukuNuku Oba-chan",
      "volume": "1",
      "last_updated": "1761557860",
      "groups": {
        "Xiffy": [
          "https://files.catbox.moe/xaceis.jpg",
          "https://files.catbox.moe/4ajw8c.jpg",
          "https://files.catbox.moe/kpucl0.jpg",
          "https://files.catbox.moe/1yakss.jpg",
          "https://files.catbox.moe/tl99mz.jpg",
          "https://files.catbox.moe/v0cskt.jpg",
          "https://files.catbox.moe/rwsmlv.jpg",
          "https://files.catbox.moe/5skvz9.jpg",
          "https://files.catbox.moe/9su98j.jpg",
          "https://files.catbox.moe/djxwvm.jpg",
          "https://files.catbox.moe/xz519a.jpg",
          "https://files.catbox.moe/lzeco0.jpg",
          "https://files.catbox.moe/9j7r95.jpg",
          "https://files.catbox.moe/o5aet4.jpg",
          "https://files.catbox.moe/l2qpnx.jpg",
          "https://files.catbox.moe/qiscns.jpg",
          "https://files.catbox.moe/kw5fk0.jpg",
          "https://files.catbox.moe/l0fnu0.jpg",
          "https://files.catbox.moe/5zwegv.jpg",
          "https://files.catbox.moe/9lhzsk.jpg",
          "https://files.catbox.moe/wybtwp.jpg",
          "https://files.catbox.moe/ybpyul.jpg",
          "https://files.catbox.moe/io0ae9.jpg",
          "https://files.catbox.moe/gujvtz.jpg",
          "https://files.catbox.moe/cp13av.jpg",
          "https://files.catbox.moe/y37our.jpg",
          "https://files.catbox.moe/mdduxs.jpg",
          "https://files.catbox.moe/5tsiw6.jpg",
          "https://files.catbox.moe/fu4e1k.jpg",
          "https://files.catbox.moe/147gvt.jpg",
          "https://files.catbox.moe/qp1v9b.jpg",
          "https://files.catbox.moe/o4l2lo.jpg",
          "https://files.catbox.moe/izb6j5.jpg",
          "https://files.catbox.moe/m27bi7.jpg",
          "https://files.catbox.moe/02ziv6.jpg",
          "https://files.catbox.moe/jgabfq.jpg",
          "https://files.catbox.moe/80gmfs.jpg",
          "https://files.catbox.moe/cgrl6r.jpg"
        ]
      }
    },
    "3": {
      "title": "03 - Shin Mama o Netoruze!",
      "volume": "1",
      "last_updated": "1761561037",
      "groups": {
        "Xiffy": [
          "https://files.catbox.moe/ywgpyv.jpg",
          "https://files.catbox.moe/bn8fcw.jpg",
          "https://files.catbox.moe/47v5yv.jpg",
          "https://files.catbox.moe/fwk0h6.jpg",
          "https://files.catbox.moe/l2blml.jpg",
          "https://files.catbox.moe/9g1ef8.jpg",
          "https://files.catbox.moe/u80fdc.jpg",
          "https://files.catbox.moe/6o0c3x.jpg",
          "https://files.catbox.moe/48u3oy.jpg",
          "https://files.catbox.moe/zm7b11.jpg",
          "https://files.catbox.moe/74lgni.jpg",
          "https://files.catbox.moe/cw6yy3.jpg",
          "https://files.catbox.moe/wzshu0.jpg",
          "https://files.catbox.moe/oyr205.jpg",
          "https://files.catbox.moe/qel2cb.jpg",
          "https://files.catbox.moe/yp7kzq.jpg",
          "https://files.catbox.moe/ynlpwz.jpg",
          "https://files.catbox.moe/s94f4l.jpg",
          "https://files.catbox.moe/3l8lpt.jpg",
          "https://files.catbox.moe/p18xem.jpg",
          "https://files.catbox.moe/fea51u.jpg",
          "https://files.catbox.moe/r76k5e.jpg",
          "https://files.catbox.moe/colc1l.jpg",
          "https://files.catbox.moe/70hibc.jpg",
          "https://files.catbox.moe/c02s2c.jpg",
          "https://files.catbox.moe/can4i2.jpg",
          "https://files.catbox.moe/wnke3i.jpg",
          "https://files.catbox.moe/wzzslx.jpg",
          "https://files.catbox.moe/niso43.jpg",
          "https://files.catbox.moe/tkwtym.jpg",
          "https://files.catbox.moe/fzgr28.jpg",
          "https://files.catbox.moe/0iymwu.jpg",
          "https://files.catbox.moe/achs7k.jpg",
          "https://files.catbox.moe/danp1h.jpg",
          "https://files.catbox.moe/30bwe8.jpg",
          "https://files.catbox.moe/7qft65.jpg",
          "https://files.catbox.moe/eumiyb.jpg",
          "https://files.catbox.moe/ajqqa7.jpg",
          "https://files.catbox.moe/8bmqx2.jpg",
          "https://files.catbox.moe/c1nnkb.jpg",
          "https://files.catbox.moe/16enn8.jpg",
          "https://files.catbox.moe/yxi0ja.jpg",
          "https://files.catbox.moe/yhzn89.jpg",
          "https://files.catbox.moe/tnafra.jpg",
          "https://files.catbox.moe/t6knop.jpg",
          "https://files.catbox.moe/635fxt.jpg",
          "https://files.catbox.moe/lks60g.jpg",
          "https://files.catbox.moe/dh3tpa.jpg"
        ]
      }
    },
    "4": {
      "title": "04 - Oba-san Taku de Asedaku de, Hitasura Sex ni Hagemu!",
      "volume": "1",
      "last_updated": "1761561689",
      "groups": {
        "Xiffy": [
          "https://files.catbox.moe/p4e2ce.jpg",
          "https://files.catbox.moe/t3v2eq.jpg",
          "https://files.catbox.moe/rxw9xt.jpg",
          "https://files.catbox.moe/16crh0.jpg",
          "https://files.catbox.moe/5hboyc.jpg",
          "https://files.catbox.moe/nzhatj.jpg",
          "https://files.catbox.moe/e1sw72.jpg",
          "https://files.catbox.moe/hzvfky.jpg",
          "https://files.catbox.moe/uhdez5.jpg",
          "https://files.catbox.moe/sd7x37.jpg",
          "https://files.catbox.moe/m6pyzw.jpg",
          "https://files.catbox.moe/gs9f9p.jpg",
          "https://files.catbox.moe/lwvnsn.jpg",
          "https://files.catbox.moe/rgohd0.jpg",
          "https://files.catbox.moe/fmdgkc.jpg",
          "https://files.catbox.moe/6urhat.jpg",
          "https://files.catbox.moe/kd5hdi.jpg",
          "https://files.catbox.moe/mhn2as.jpg",
          "https://files.catbox.moe/vdilvg.jpg",
          "https://files.catbox.moe/a1sttd.jpg",
          "https://files.catbox.moe/a7cm91.jpg",
          "https://files.catbox.moe/bkxrfn.jpg",
          "https://files.catbox.moe/m04c9r.jpg",
          "https://files.catbox.moe/x6w74o.jpg",
          "https://files.catbox.moe/ggzftw.jpg",
          "https://files.catbox.moe/9zjssn.jpg",
          "https://files.catbox.moe/q8vzhs.jpg",
          "https://files.catbox.moe/c8gy0h.jpg",
          "https://files.catbox.moe/565uak.jpg",
          "https://files.catbox.moe/kd8lya.jpg",
          "https://files.catbox.moe/jjmorz.jpg",
          "https://files.catbox.moe/b7ii2s.jpg",
          "https://files.catbox.moe/budhex.jpg",
          "https://files.catbox.moe/s00j8d.jpg"
        ]
      }
    },
    "5": {
      "title": "05 - Shin Mama wo Netoruze! 2",
      "volume": "1",
      "last_updated": "1761562180",
      "groups": {
        "Xiffy": [
          "https://files.catbox.moe/uznpyp.jpg",
          "https://files.catbox.moe/kei6fn.jpg",
          "https://files.catbox.moe/iejoho.jpg",
          "https://files.catbox.moe/4sv8kj.jpg",
          "https://files.catbox.moe/m4olnb.jpg",
          "https://files.catbox.moe/jhpwcr.jpg",
          "https://files.catbox.moe/oqvcki.jpg",
          "https://files.catbox.moe/02odor.jpg",
          "https://files.catbox.moe/majbdz.jpg",
          "https://files.catbox.moe/z33ncd.jpg",
          "https://files.catbox.moe/zk2c7b.jpg",
          "https://files.catbox.moe/ytp63r.jpg",
          "https://files.catbox.moe/qazdn2.jpg",
          "https://files.catbox.moe/3p8g3d.jpg",
          "https://files.catbox.moe/sassb0.jpg",
          "https://files.catbox.moe/5v27bg.jpg",
          "https://files.catbox.moe/d3eex2.jpg",
          "https://files.catbox.moe/gizkut.jpg",
          "https://files.catbox.moe/j9fxwk.jpg",
          "https://files.catbox.moe/olbbv9.jpg",
          "https://files.catbox.moe/19iaal.jpg",
          "https://files.catbox.moe/ks98fi.jpg",
          "https://files.catbox.moe/6ytngo.jpg",
          "https://files.catbox.moe/22udv1.jpg",
          "https://files.catbox.moe/cndweb.jpg",
          "https://files.catbox.moe/dmm7lf.jpg",
          "https://files.catbox.moe/pcafdd.jpg",
          "https://files.catbox.moe/iqpo6w.jpg",
          "https://files.catbox.moe/5usvlk.jpg",
          "https://files.catbox.moe/3o1z0o.jpg",
          "https://files.catbox.moe/ubz6gg.jpg",
          "https://files.catbox.moe/yinusf.jpg",
          "https://files.catbox.moe/2btx6n.jpg",
          "https://files.catbox.moe/r449g6.jpg",
          "https://files.catbox.moe/fqcqys.jpg",
          "https://files.catbox.moe/991haw.jpg",
          "https://files.catbox.moe/kndbn1.jpg",
          "https://files.catbox.moe/6tufep.jpg",
          "https://files.catbox.moe/gytryv.jpg",
          "https://files.catbox.moe/jdlm6o.jpg"
        ]
      }
    },
    "6": {
      "title": "06 - NukuChan",
      "volume": "1",
      "last_updated": "1761565041",
      "groups": {
        "Xiffy": [
          "https://files.catbox.moe/376obo.jpg",
          "https://files.catbox.moe/4vijx6.jpg",
          "https://files.catbox.moe/5g2mqs.jpg",
          "https://files.catbox.moe/k3cf0a.jpg",
          "https://files.catbox.moe/r9pwhx.jpg",
          "https://files.catbox.moe/beqwdg.jpg",
          "https://files.catbox.moe/qmenku.jpg",
          "https://files.catbox.moe/s4his5.jpg",
          "https://files.catbox.moe/dr33r4.jpg",
          "https://files.catbox.moe/ingxec.jpg",
          "https://files.catbox.moe/0ldz9p.jpg",
          "https://files.catbox.moe/rcebk4.jpg",
          "https://files.catbox.moe/46vqzb.jpg",
          "https://files.catbox.moe/3sybqx.jpg",
          "https://files.catbox.moe/0ty6vs.jpg",
          "https://files.catbox.moe/yuoj86.jpg",
          "https://files.catbox.moe/j2l495.jpg",
          "https://files.catbox.moe/m8su2i.jpg",
          "https://files.catbox.moe/fa3o9g.jpg",
          "https://files.catbox.moe/y75vrm.jpg",
          "https://files.catbox.moe/sf2dxy.jpg",
          "https://files.catbox.moe/0c468f.jpg",
          "https://files.catbox.moe/pv9ev4.jpg",
          "https://files.catbox.moe/vef1hk.jpg",
          "https://files.catbox.moe/el0xtm.jpg",
          "https://files.catbox.moe/j793a8.jpg",
          "https://files.catbox.moe/ote6rd.jpg",
          "https://files.catbox.moe/5kl5zd.jpg",
          "https://files.catbox.moe/7lu4mu.jpg",
          "https://files.catbox.moe/zgpe1h.jpg",
          "https://files.catbox.moe/eed9wx.jpg",
          "https://files.catbox.moe/v19gxq.jpg",
          "https://files.catbox.moe/gsfuj4.jpg",
          "https://files.catbox.moe/wo6mom.jpg",
          "https://files.catbox.moe/an7os3.jpg",
          "https://files.catbox.moe/xiifhw.jpg",
          "https://files.catbox.moe/c51gyi.jpg",
          "https://files.catbox.moe/8atk71.jpg",
          "https://files.catbox.moe/poqcpt.jpg",
          "https://files.catbox.moe/avlg2f.jpg",
          "https://files.catbox.moe/uz7w3n.jpg",
          "https://files.catbox.moe/6mj19o.jpg",
          "https://files.catbox.moe/o2m14u.jpg",
          "https://files.catbox.moe/5bmyss.jpg",
          "https://files.catbox.moe/qgae78.jpg",
          "https://files.catbox.moe/zjlugx.jpg",
          "https://files.catbox.moe/kfwffw.jpg",
          "https://files.catbox.moe/f02ayf.jpg",
          "https://files.catbox.moe/yqwfqk.jpg",
          "https://files.catbox.moe/y7acbh.jpg"
        ]
      }
    },
    "7": {
      "title": "07 - Kinshin Rankou",
      "volume": "1",
      "last_updated": "1761566615",
      "groups": {
        "Xiffy": [
          "https://files.catbox.moe/f5120m.jpg",
          "https://files.catbox.moe/01si00.jpg",
          "https://files.catbox.moe/jsds55.jpg",
          "https://files.catbox.moe/p2raao.jpg",
          "https://files.catbox.moe/gbz1sk.jpg",
          "https://files.catbox.moe/rtkrk2.jpg",
          "https://files.catbox.moe/bm10jy.jpg",
          "https://files.catbox.moe/43gpat.jpg",
          "https://files.catbox.moe/tt7ijq.jpg",
          "https://files.catbox.moe/j5euwr.jpg",
          "https://files.catbox.moe/zue19b.jpg",
          "https://files.catbox.moe/697k86.jpg",
          "https://files.catbox.moe/ipt42l.jpg",
          "https://files.catbox.moe/gtrhup.jpg",
          "https://files.catbox.moe/qukvld.jpg",
          "https://files.catbox.moe/kunlit.jpg",
          "https://files.catbox.moe/svabzc.jpg",
          "https://files.catbox.moe/khyppq.jpg",
          "https://files.catbox.moe/a8gemy.jpg",
          "https://files.catbox.moe/r264yn.jpg",
          "https://files.catbox.moe/dgwp0r.jpg",
          "https://files.catbox.moe/s3rxp0.jpg",
          "https://files.catbox.moe/axdh9e.jpg",
          "https://files.catbox.moe/lo8egw.jpg",
          "https://files.catbox.moe/tsdoar.jpg",
          "https://files.catbox.moe/dlbfdq.jpg",
          "https://files.catbox.moe/zn3h3g.jpg",
          "https://files.catbox.moe/zgs3p4.jpg",
          "https://files.catbox.moe/m29jr8.jpg",
          "https://files.catbox.moe/7ceihz.jpg",
          "https://files.catbox.moe/mnk25t.jpg",
          "https://files.catbox.moe/wa1r1c.jpg",
          "https://files.catbox.moe/r6ygzr.jpg",
          "https://files.catbox.moe/o3h8i0.jpg",
          "https://files.catbox.moe/d0wn7t.jpg",
          "https://files.catbox.moe/v600eo.jpg",
          "https://files.catbox.moe/mln9fn.jpg",
          "https://files.catbox.moe/x4kh5k.jpg",
          "https://files.catbox.moe/mwgb31.jpg",
          "https://files.catbox.moe/lsqxs7.jpg"
        ]
      }
    },
    "8": {
      "title": "08 - Adultery Feast",
      "volume": "1",
      "last_updated": "1761569630",
      "groups": {
        "Xiffy": [
          "https://files.catbox.moe/yhhy5x.jpg",
          "https://files.catbox.moe/6wzac5.jpg",
          "https://files.catbox.moe/6wqx0q.jpg",
          "https://files.catbox.moe/xyba5f.jpg",
          "https://files.catbox.moe/xollyr.jpg",
          "https://files.catbox.moe/tqhba1.jpg",
          "https://files.catbox.moe/8x6jul.jpg",
          "https://files.catbox.moe/w4akqw.jpg",
          "https://files.catbox.moe/0e3x9q.jpg",
          "https://files.catbox.moe/v4quow.jpg",
          "https://files.catbox.moe/fwr14l.jpg",
          "https://files.catbox.moe/jeyzp9.jpg",
          "https://files.catbox.moe/gi3hip.jpg",
          "https://files.catbox.moe/f2lp0h.jpg",
          "https://files.catbox.moe/6hf5az.jpg",
          "https://files.catbox.moe/19dst5.jpg",
          "https://files.catbox.moe/b2oprg.jpg",
          "https://files.catbox.moe/rvnkna.jpg",
          "https://files.catbox.moe/jrhexz.jpg",
          "https://files.catbox.moe/6o0zaa.jpg",
          "https://files.catbox.moe/a3misu.jpg",
          "https://files.catbox.moe/hdr171.jpg",
          "https://files.catbox.moe/p9k4jp.jpg",
          "https://files.catbox.moe/bisid2.jpg",
          "https://files.catbox.moe/bx8h33.jpg",
          "https://files.catbox.moe/h5ffys.jpg",
          "https://files.catbox.moe/pd4s94.jpg",
          "https://files.catbox.moe/mzcjcz.jpg",
          "https://files.catbox.moe/z2i8kh.jpg",
          "https://files.catbox.moe/m5986q.jpg",
          "https://files.catbox.moe/aa336y.jpg",
          "https://files.catbox.moe/nj4kdk.jpg",
          "https://files.catbox.moe/qznzsg.jpg",
          "https://files.catbox.moe/1hex82.jpg",
          "https://files.catbox.moe/hffv12.jpg",
          "https://files.catbox.moe/6rz8fy.jpg",
          "https://files.catbox.moe/y8h8ok.jpg",
          "https://files.catbox.moe/p0yche.jpg",
          "https://files.catbox.moe/x7wcnf.jpg",
          "https://files.catbox.moe/ahy5j0.jpg",
          "https://files.catbox.moe/qschf5.jpg",
          "https://files.catbox.moe/iws9j3.jpg",
          "https://files.catbox.moe/p80ce8.jpg",
          "https://files.catbox.moe/25evnf.jpg",
          "https://files.catbox.moe/rcc1i1.jpg",
          "https://files.catbox.moe/c26y62.jpg",
          "https://files.catbox.moe/4b0tkl.jpg",
          "https://files.catbox.moe/ojmcuc.jpg",
          "https://files.catbox.moe/480bw4.jpg",
          "https://files.catbox.moe/hemsz3.jpg",
          "https://files.catbox.moe/uoi2y9.jpg",
          "https://files.catbox.moe/pudaao.jpg",
          "https://files.catbox.moe/73fxfv.jpg",
          "https://files.catbox.moe/7c9d5a.jpg"
        ]
      }
    },
    "9": {
      "title": "09 - Shigeo Fever!",
      "volume": "1",
      "last_updated": "1761570724",
      "groups": {
        "Xiffy": [
          "https://files.catbox.moe/73m84q.jpg",
          "https://files.catbox.moe/1nh94v.jpg",
          "https://files.catbox.moe/6h2s6c.jpg",
          "https://files.catbox.moe/w8zsm5.jpg",
          "https://files.catbox.moe/003l55.jpg",
          "https://files.catbox.moe/pz0ywp.jpg",
          "https://files.catbox.moe/rl8h5b.jpg",
          "https://files.catbox.moe/6pkymd.jpg",
          "https://files.catbox.moe/3waaot.jpg",
          "https://files.catbox.moe/efin37.jpg",
          "https://files.catbox.moe/txua4c.jpg",
          "https://files.catbox.moe/rfxcz4.jpg",
          "https://files.catbox.moe/qd759w.jpg",
          "https://files.catbox.moe/g6cdvq.jpg",
          "https://files.catbox.moe/rwh1fv.jpg",
          "https://files.catbox.moe/9ruce8.jpg",
          "https://files.catbox.moe/m8ecsr.jpg",
          "https://files.catbox.moe/o4pbzj.jpg",
          "https://files.catbox.moe/rl89x0.jpg",
          "https://files.catbox.moe/sd1nfy.jpg",
          "https://files.catbox.moe/qa3r19.jpg",
          "https://files.catbox.moe/snljm1.jpg",
          "https://files.catbox.moe/7mue0p.jpg",
          "https://files.catbox.moe/g1tr9k.jpg",
          "https://files.catbox.moe/cq66gb.jpg",
          "https://files.catbox.moe/3donl4.jpg",
          "https://files.catbox.moe/j1kxas.jpg",
          "https://files.catbox.moe/pif5eq.jpg",
          "https://files.catbox.moe/7j1u2t.jpg",
          "https://files.catbox.moe/ucl8kg.jpg",
          "https://files.catbox.moe/6wv75u.jpg",
          "https://files.catbox.moe/1ce8m5.jpg",
          "https://files.catbox.moe/yk7u43.jpg",
          "https://files.catbox.moe/rp1mos.jpg",
          "https://files.catbox.moe/o6ds07.jpg",
          "https://files.catbox.moe/unbhsz.jpg",
          "https://files.catbox.moe/myluhq.jpg",
          "https://files.catbox.moe/ys97jz.jpg",
          "https://files.catbox.moe/3kfhce.jpg",
          "https://files.catbox.moe/d4ewbk.jpg",
          "https://files.catbox.moe/25myau.jpg",
          "https://files.catbox.moe/52joez.jpg",
          "https://files.catbox.moe/jta3n6.jpg",
          "https://files.catbox.moe/vsn01q.jpg",
          "https://files.catbox.moe/t5r9h3.jpg",
          "https://files.catbox.moe/8d21c1.jpg",
          "https://files.catbox.moe/mlnap2.jpg",
          "https://files.catbox.moe/l174hq.jpg",
          "https://files.catbox.moe/wt8d6r.jpg",
          "https://files.catbox.moe/luqbxu.jpg",
          "https://files.catbox.moe/lb36n2.jpg",
          "https://files.catbox.moe/glcn6i.jpg",
          "https://files.catbox.moe/do37aq.jpg",
          "https://files.catbox.moe/it4jwh.jpg",
          "https://files.catbox.moe/kiizdu.jpg"
        ]
      }
    },
    "10": {
      "title": "10 - Oba to 3P _ It's Family Fun for Three",
      "volume": "1",
      "last_updated": "1761570872",
      "groups": {
        "Xiffy": [
          "https://files.catbox.moe/bfjqkf.jpg",
          "https://files.catbox.moe/8g0iti.jpg",
          "https://files.catbox.moe/l7h7pm.jpg",
          "https://files.catbox.moe/ljwzay.jpg",
          "https://files.catbox.moe/0rm0nc.jpg",
          "https://files.catbox.moe/0v2x77.jpg",
          "https://files.catbox.moe/ng6oc2.jpg",
          "https://files.catbox.moe/lvq6em.jpg",
          "https://files.catbox.moe/ltkego.jpg",
          "https://files.catbox.moe/jjv6qu.jpg",
          "https://files.catbox.moe/9eezpz.jpg",
          "https://files.catbox.moe/amp3tq.jpg",
          "https://files.catbox.moe/k0mjy0.jpg",
          "https://files.catbox.moe/0ai8x4.jpg",
          "https://files.catbox.moe/mxmsxv.jpg",
          "https://files.catbox.moe/choeam.jpg",
          "https://files.catbox.moe/6hvil5.jpg",
          "https://files.catbox.moe/cua54i.jpg",
          "https://files.catbox.moe/5ib28n.jpg",
          "https://files.catbox.moe/07lae2.jpg",
          "https://files.catbox.moe/p08ykz.jpg",
          "https://files.catbox.moe/c9ufko.jpg",
          "https://files.catbox.moe/gj7zro.jpg",
          "https://files.catbox.moe/xoxcc9.jpg",
          "https://files.catbox.moe/wa2ifa.jpg",
          "https://files.catbox.moe/q4cupd.jpg",
          "https://files.catbox.moe/ckxybb.jpg",
          "https://files.catbox.moe/leumx2.jpg",
          "https://files.catbox.moe/u9gec3.jpg"
        ]
      }
    },
    "11": {}
  }
}