{
  "title": "Youta",
  "description": "Youta and aunt Saeko by Freehand Tamashii",
  "artist": "Freehand Tamashii",
  "author": "Freehand Tamashii",
  "cover": "https://files.catbox.moe/2islgz.jpg",
  "chapters": {
    "002": {
      "title": "- Okazu wa Kyou mo, Tsuma no Botebara Noukou Sex",
      "last_updated": "1772566105",
      "groups": {
        "Xiffy": "/proxy/api/imgchest/chapter/9p4n63nb57n"
      }
    },
    "001": {
      "title": "- Isourou Saki no Obasan ni Hameru!",
      "last_updated": "1772566121",
      "groups": {
        "Xiffy": "/proxy/api/imgchest/chapter/ne7b325mgy5"
      }
    }
  }
}